tileget/__init__.py
tileget/__main__.py
tileget/arg.py
tileget-1.0.1.dist-info/WHEEL
tileget-1.0.1.dist-info/entry_points.txt
tileget-1.0.1.dist-info/METADATA
tileget-1.0.1.dist-info/RECORD
