Metadata-Version: 2.3
Name: tileget
Version: 1.0.1
Summary: Tile download utility - easily download xyz-tile data
Requires-Dist: shapely>=2.0.3
Requires-Dist: tiletanic>=1.1.0
Requires-Dist: pyproj>=3.6.1
Requires-Dist: httpx>=0.28
Requires-Python: >=3.14
